syntaxiperror/__init__.py
syntaxiperror/__main__.py
syntaxiperror/error.py
syntaxiperror/validates.py
syntaxiperror-0.1.dev0.dist-info/METADATA
syntaxiperror-0.1.dev0.dist-info/WHEEL
syntaxiperror-0.1.dev0.dist-info/entry_points.txt
syntaxiperror-0.1.dev0.dist-info/top_level.txt
syntaxiperror-0.1.dev0.dist-info/RECORD
